jaguar/__init__.py
jaguar/cli.py
jaguar/jaguar.py
jaguar-0.1.1.dist-info/AUTHORS.rst
jaguar-0.1.1.dist-info/LICENSE
jaguar-0.1.1.dist-info/METADATA
jaguar-0.1.1.dist-info/WHEEL
jaguar-0.1.1.dist-info/entry_points.txt
jaguar-0.1.1.dist-info/top_level.txt
jaguar-0.1.1.dist-info/RECORD
