Metadata-Version: 2.1
Name: jaguar
Version: 0.1.1
Summary: Full Stack Python Web Framework
Home-page: https://github.com/ourway/jaguar
Author: Farshid Ashouri
Author-email: farsheed.ashouri@gmail.com
License: MIT license
Keywords: jaguar
Platform: UNKNOWN
Classifier: Development Status :: 2 - Pre-Alpha
Classifier: Intended Audience :: Developers
Classifier: License :: OSI Approved :: MIT License
Classifier: Natural Language :: English
Classifier: Programming Language :: Python :: 3
Classifier: Programming Language :: Python :: 3.5
Classifier: Programming Language :: Python :: 3.6
Classifier: Programming Language :: Python :: 3.7
Classifier: Programming Language :: Python :: 3.8
Requires-Python: >=3.8
